.gitignore
.readthedocs.yml
CHANGES.rst
CODE_OF_CONDUCT.md
CONTRIBUTING.md
LICENSE.rst
MANIFEST.in
README.rst
pyproject.toml
setup.cfg
setup.py
tox.ini
.github/workflows/ci.yml
docs/Makefile
docs/source/conf.py
docs/source/index.rst
docs/source/_static/theme_overrides.css
jirahub/__init__.py
jirahub/command_line.py
jirahub/config.py
jirahub/entities.py
jirahub/github.py
jirahub/jira.py
jirahub/jirahub.py
jirahub/permissions.py
jirahub/utils.py
jirahub.egg-info/PKG-INFO
jirahub.egg-info/SOURCES.txt
jirahub.egg-info/dependency_links.txt
jirahub.egg-info/entry_points.txt
jirahub.egg-info/not-zip-safe
jirahub.egg-info/requires.txt
jirahub.egg-info/top_level.txt
jirahub/resources/__init__.py
jirahub/resources/config_template.py
tests/__init__.py
tests/conftest.py
tests/constants.py
tests/mocks.py
tests/test_command_line.py
tests/test_config.py
tests/test_entities.py
tests/test_github.py
tests/test_jira.py
tests/test_jirahub.py
tests/test_permissions.py
tests/test_utils.py
tests/configs/bad_config.py
tests/configs/fragment_config_base.py
tests/configs/fragment_config_failing.py
tests/configs/fragment_config_overrides.py
tests/configs/full_config.py
tests/configs/incomplete_config.py
tests/configs/minimal_config.py