Metadata-Version: 2.1
Name: jirahub
Version: 0.3.0
Summary: A package for syncing JIRA tickets and GitHub issues
Home-page: https://github.com/spacetelescope/jirahub
Author: STScI
Author-email: help@stsci.edu
License: BSD 3-Clause
Platform: UNKNOWN
Provides: jirahub
Requires-Python: >=3.7
Provides-Extra: dev
Provides-Extra: docs
